countdown/__init__.py
countdown/__main__.py
countdown/digits.py
countdown/display.py
countdown/glyphs.txt
countdown/keys.py
countdown/terminal.py
countdown/timer.py
countdown_cli-2.1.0.dist-info/METADATA
countdown_cli-2.1.0.dist-info/WHEEL
countdown_cli-2.1.0.dist-info/entry_points.txt
countdown_cli-2.1.0.dist-info/licenses/LICENSE.rst
countdown_cli-2.1.0.dist-info/RECORD
