Metadata-Version: 2.4
Name: countdown-cli
Version: 2.1.0
Summary: Terminal program to display countdown timer
Project-URL: homepage, https://github.com/treyhunner/countdown-cli
Project-URL: repository, https://github.com/treyhunner/countdown-cli
Project-URL: Changelog, https://github.com/treyhunner/countdown-cli/releases
Author: Trey Hunner
License: MIT
License-File: LICENSE.rst
Classifier: Development Status :: 4 - Beta
Classifier: Programming Language :: Python :: 3.10
Classifier: Programming Language :: Python :: 3.11
Classifier: Programming Language :: Python :: 3.12
Classifier: Programming Language :: Python :: 3.13
Classifier: Programming Language :: Python :: 3.14
Classifier: Programming Language :: Python :: 3.15
Requires-Python: >=3.10
Requires-Dist: click>=8.3.0
